LICENCE.txt
MANIFEST.in
README.rst
setup.cfg
setup.py
html_checker/__init__.py
html_checker/exceptions.py
html_checker/logger.py
html_checker/reporter.py
html_checker/serve.py
html_checker/sitemap.py
html_checker/validator.py
html_checker/cli/__init__.py
html_checker/cli/common.py
html_checker/cli/entrypoint.py
html_checker/cli/page.py
html_checker/cli/site.py
html_checker/cli/version.py
html_checker/export/__init__.py
html_checker/export/base.py
html_checker/export/jinja.py
html_checker/export/jinja_filters.py
html_checker/export/json.py
html_checker/export/logs.py
html_checker/export/render.py
html_checker/utils/__init__.py
html_checker/utils/commands.py
html_checker/utils/documents.py
html_checker/utils/paths.py
html_checker/utils/server.py
html_checker/utils/structures.py
html_checker/utils/tests.py
html_checker/utils/texts.py
html_checker/vnujar/vnu.jar
py_html_checker.egg-info/PKG-INFO
py_html_checker.egg-info/SOURCES.txt
py_html_checker.egg-info/dependency_links.txt
py_html_checker.egg-info/entry_points.txt
py_html_checker.egg-info/requires.txt
py_html_checker.egg-info/top_level.txt
py_html_checker.egg-info/zip-safe