Metadata-Version: 2.1
Name: py-html-checker
Version: 0.5.0
Summary: Python wrapper around library Nu Html Checker (v.Nu)
Home-page: https://github.com/sveetch/py-html-checker
Author: David Thenon
Author-email: sveetch@gmail.com
License: MIT
Project-URL: Source Code, https://github.com/sveetch/py-html-checker
Project-URL: Issue Tracker, https://github.com/sveetch/py-html-checker/issues
Project-URL: Changelog, https://py-html-checker.readthedocs.io/en/latest/history.html
Project-URL: Documentation, https://py-html-checker.readthedocs.io/
Keywords: Python,HTML,VNU
Classifier: Development Status :: 5 - Production/Stable
Classifier: Intended Audience :: Developers
Classifier: License :: OSI Approved :: MIT License
Classifier: Natural Language :: English
Classifier: Programming Language :: Python :: 3
Classifier: Programming Language :: Python :: 3.8
Classifier: Programming Language :: Python :: 3.9
Classifier: Programming Language :: Python :: 3.10
Requires-Python: >=3.8
License-File: LICENCE.txt
Requires-Dist: requests
Provides-Extra: cli
Requires-Dist: click>=7.0; extra == "cli"
Requires-Dist: colorlog; extra == "cli"
Provides-Extra: jinja
Requires-Dist: Jinja2>=3.0; extra == "jinja"
Requires-Dist: Pygments>=2.6.0; extra == "jinja"
Provides-Extra: serve
Requires-Dist: cherrypy>=18.0.0; extra == "serve"
Provides-Extra: dev
Requires-Dist: pytest; extra == "dev"
Provides-Extra: quality
Requires-Dist: flake8; extra == "quality"
Requires-Dist: tox; extra == "quality"
Requires-Dist: twine; extra == "quality"
Provides-Extra: doc
Requires-Dist: sphinx>=8.0.2; extra == "doc"
Requires-Dist: furo>=2024.8.6; extra == "doc"
Requires-Dist: sphinx-copybutton>=0.5.2; extra == "doc"
Provides-Extra: doc-live
Requires-Dist: livereload; extra == "doc-live"
